{
  "schema_version": "2.0",
  "updated_at": "2026-07-15 02:18:02",
  "issues": [
    {
      "code": "field_conflict",
      "message": "conflicting heat",
      "severity": "warning",
      "game_id": 165287,
      "platform": null,
      "chart": null,
      "field": "heat",
      "values": [
        51252251,
        51252255
      ]
    },
    {
      "code": "field_conflict",
      "message": "conflicting heat",
      "severity": "warning",
      "game_id": 45213,
      "platform": null,
      "chart": null,
      "field": "heat",
      "values": [
        58601198,
        58601200
      ]
    },
    {
      "code": "field_conflict",
      "message": "conflicting heat",
      "severity": "warning",
      "game_id": 234280,
      "platform": null,
      "chart": null,
      "field": "heat",
      "values": [
        22747787,
        22747790
      ]
    },
    {
      "code": "field_conflict",
      "message": "conflicting heat",
      "severity": "warning",
      "game_id": 206776,
      "platform": null,
      "chart": null,
      "field": "heat",
      "values": [
        38479411,
        38479412
      ]
    },
    {
      "code": "field_conflict",
      "message": "conflicting heat",
      "severity": "warning",
      "game_id": 58881,
      "platform": null,
      "chart": null,
      "field": "heat",
      "values": [
        273511652,
        273511654
      ]
    },
    {
      "code": "field_conflict",
      "message": "conflicting heat",
      "severity": "warning",
      "game_id": 815993,
      "platform": null,
      "chart": null,
      "field": "heat",
      "values": [
        2753410,
        2753415
      ]
    },
    {
      "code": "field_conflict",
      "message": "conflicting heat",
      "severity": "warning",
      "game_id": 714123,
      "platform": null,
      "chart": null,
      "field": "heat",
      "values": [
        17133462,
        17133466
      ]
    },
    {
      "code": "field_conflict",
      "message": "conflicting heat",
      "severity": "warning",
      "game_id": 62448,
      "platform": null,
      "chart": null,
      "field": "heat",
      "values": [
        43805694,
        43805695
      ]
    },
    {
      "code": "field_conflict",
      "message": "conflicting heat",
      "severity": "warning",
      "game_id": 330259,
      "platform": null,
      "chart": null,
      "field": "heat",
      "values": [
        19942091,
        19942092
      ]
    },
    {
      "code": "field_conflict",
      "message": "conflicting heat",
      "severity": "warning",
      "game_id": 49995,
      "platform": null,
      "chart": null,
      "field": "heat",
      "values": [
        29396524,
        29396526
      ]
    },
    {
      "code": "field_conflict",
      "message": "conflicting heat",
      "severity": "warning",
      "game_id": 7698,
      "platform": null,
      "chart": null,
      "field": "heat",
      "values": [
        4404478,
        4404480
      ]
    },
    {
      "code": "field_conflict",
      "message": "conflicting heat",
      "severity": "warning",
      "game_id": 70056,
      "platform": null,
      "chart": null,
      "field": "heat",
      "values": [
        54952078,
        54952079
      ]
    },
    {
      "code": "field_conflict",
      "message": "conflicting heat",
      "severity": "warning",
      "game_id": 60809,
      "platform": null,
      "chart": null,
      "field": "heat",
      "values": [
        16421725,
        16421727
      ]
    },
    {
      "code": "field_conflict",
      "message": "conflicting heat",
      "severity": "warning",
      "game_id": 786394,
      "platform": null,
      "chart": null,
      "field": "heat",
      "values": [
        415387,
        415388
      ]
    },
    {
      "code": "field_conflict",
      "message": "conflicting heat",
      "severity": "warning",
      "game_id": 221062,
      "platform": null,
      "chart": null,
      "field": "heat",
      "values": [
        10691348,
        10691350
      ]
    },
    {
      "code": "field_conflict",
      "message": "conflicting heat",
      "severity": "warning",
      "game_id": 383776,
      "platform": null,
      "chart": null,
      "field": "heat",
      "values": [
        1896820,
        1896821
      ]
    },
    {
      "code": "field_conflict",
      "message": "conflicting heat",
      "severity": "warning",
      "game_id": 240388,
      "platform": null,
      "chart": null,
      "field": "heat",
      "values": [
        1277916,
        1277917
      ]
    },
    {
      "code": "field_conflict",
      "message": "conflicting heat",
      "severity": "warning",
      "game_id": 172095,
      "platform": null,
      "chart": null,
      "field": "heat",
      "values": [
        4402685,
        4402686
      ]
    },
    {
      "code": "field_conflict",
      "message": "conflicting heat",
      "severity": "warning",
      "game_id": 201633,
      "platform": null,
      "chart": null,
      "field": "heat",
      "values": [
        9468227,
        9468228
      ]
    },
    {
      "code": "field_conflict",
      "message": "conflicting heat",
      "severity": "warning",
      "game_id": 740298,
      "platform": null,
      "chart": null,
      "field": "heat",
      "values": [
        385523,
        385524
      ]
    },
    {
      "code": "field_conflict",
      "message": "conflicting heat",
      "severity": "warning",
      "game_id": 713640,
      "platform": null,
      "chart": null,
      "field": "heat",
      "values": [
        1643294,
        1643293
      ]
    },
    {
      "code": "field_conflict",
      "message": "conflicting heat",
      "severity": "warning",
      "game_id": 221322,
      "platform": null,
      "chart": null,
      "field": "heat",
      "values": [
        9516715,
        9516714
      ]
    },
    {
      "code": "field_conflict",
      "message": "conflicting heat",
      "severity": "warning",
      "game_id": 732091,
      "platform": null,
      "chart": null,
      "field": "heat",
      "values": [
        733090,
        733091
      ]
    },
    {
      "code": "field_conflict",
      "message": "conflicting heat",
      "severity": "warning",
      "game_id": 766491,
      "platform": null,
      "chart": null,
      "field": "heat",
      "values": [
        83868,
        83869
      ]
    },
    {
      "code": "field_conflict",
      "message": "conflicting heat",
      "severity": "warning",
      "game_id": 387279,
      "platform": null,
      "chart": null,
      "field": "heat",
      "values": [
        300445,
        300446
      ]
    },
    {
      "code": "field_conflict",
      "message": "conflicting heat",
      "severity": "warning",
      "game_id": 231086,
      "platform": null,
      "chart": null,
      "field": "heat",
      "values": [
        2078498,
        2078499
      ]
    },
    {
      "code": "field_conflict",
      "message": "conflicting heat",
      "severity": "warning",
      "game_id": 709805,
      "platform": null,
      "chart": null,
      "field": "heat",
      "values": [
        99483,
        99484
      ]
    },
    {
      "code": "field_conflict",
      "message": "conflicting heat",
      "severity": "warning",
      "game_id": 186316,
      "platform": null,
      "chart": null,
      "field": "heat",
      "values": [
        4511635,
        4511636
      ]
    },
    {
      "code": "field_conflict",
      "message": "conflicting heat",
      "severity": "warning",
      "game_id": 55307,
      "platform": null,
      "chart": null,
      "field": "heat",
      "values": [
        3798492,
        3798493
      ]
    },
    {
      "code": "field_conflict",
      "message": "conflicting heat",
      "severity": "warning",
      "game_id": 712212,
      "platform": null,
      "chart": null,
      "field": "heat",
      "values": [
        711658,
        711659
      ]
    }
  ]
}